llm_probe/__init__.py
llm_probe/version.py
llm_probe/models/__init__.py
llm_probe/models/gpt2.py
llm_probe/models/llama.py
llm_probe/models/mixtral.py
llm_probe/probe/__init__.py
llm_probe/probe/huggingface_probe.py
llm_probe/probe/pytorch_probe.py
llm_probe/probe/plugin/__init__.py
llm_probe/probe/plugin/block_sparse_moe.py
llm_probe/probe/plugin/rotary_embedding.py
llm_probe/utils/__init__.py
llm_probe-0.1.8.dist-info/METADATA
llm_probe-0.1.8.dist-info/WHEEL
llm_probe-0.1.8.dist-info/top_level.txt
llm_probe-0.1.8.dist-info/RECORD
