Metadata-Version: 2.4
Name: llm-probe
Version: 0.1.8
Summary: Extracting Intermediate Activations and Parameters from Hugging Face Models
Author: Junsoo Kim
Author-email: Junsoo Kim <js.kim@hyperaccel.ai>
Requires-Python: >=3.10
Requires-Dist: transformers<=4.48.0,>=4.45.0
Requires-Dist: torch==2.4.0
Dynamic: author
